image_formatter/__init__.py
image_formatter/error_handler/__init__.py
image_formatter/error_handler/error_handler.py
image_formatter/error_handler/errors.py
image_formatter/image_formatter_plugin/__init__.py
image_formatter/image_formatter_plugin/image_formatter_plugin.py
image_formatter/image_properties_tag_replacer/__init__.py
image_formatter/image_properties_tag_replacer/image_properties_tag_replacer.py
image_formatter/lexer/__init__.py
image_formatter/lexer/lexer.py
image_formatter/lexer/position.py
image_formatter/lexer/token.py
image_formatter/lexer/token_stream_processor.py
image_formatter/token_to_string_converter/__init__.py
image_formatter/token_to_string_converter/token_to_string_converter.py
tests/__init__.py
tests/test_helpers.py
tests/image_formatter_plugin/__init__.py
tests/image_formatter_plugin/test_e2e_image_formatter_plugin.py
tests/image_formatter_plugin/test_image_formatter_plugin.py
tests/image_properties_tag_replacer/__init__.py
tests/image_properties_tag_replacer/test_image_properties_tag_replacer_exceptions.py
tests/image_properties_tag_replacer/test_integration_image_properties_tag_replacer_lexer.py
tests/image_properties_tag_replacer/test_unit_image_properties_tag_replacer.py
tests/lexer/__init__.py
tests/lexer/test_acceptance_lexer.py
tests/lexer/test_hypothesis_lexer.py
tests/lexer/test_unit_lexer.py
tests/token_to_string_converter/__init__.py
tests/token_to_string_converter/test_unit_token_to_string_converter.py
mkdocs_image_formatter_plugin-1.0.0.dist-info/LICENSE
mkdocs_image_formatter_plugin-1.0.0.dist-info/METADATA
mkdocs_image_formatter_plugin-1.0.0.dist-info/WHEEL
mkdocs_image_formatter_plugin-1.0.0.dist-info/entry_points.txt
mkdocs_image_formatter_plugin-1.0.0.dist-info/top_level.txt
mkdocs_image_formatter_plugin-1.0.0.dist-info/RECORD
